mcp_data_analyzer_assistant/__init__.py
mcp_data_analyzer_assistant/__main__.py
mcp_data_analyzer_assistant/cli.py
mcp_data_analyzer_assistant/core.py
mcp_data_analyzer_assistant-0.1.5.dist-info/METADATA
mcp_data_analyzer_assistant-0.1.5.dist-info/WHEEL
mcp_data_analyzer_assistant-0.1.5.dist-info/entry_points.txt
mcp_data_analyzer_assistant-0.1.5.dist-info/top_level.txt
mcp_data_analyzer_assistant-0.1.5.dist-info/RECORD
