Metadata-Version: 2.4
Name: mcp-data-analyzer-assistant
Version: 0.1.5
Summary: 通用分析助手
Requires-Python: >=3.13
Requires-Dist: mcp[cli]>=1.15.0
Requires-Dist: openpyxl>=3.1.5
Requires-Dist: pandas>=2.3.3
Requires-Dist: seaborn>=0.13.2
Requires-Dist: twine>=6.2.0
